tensorkrowch/__init__.py
tensorkrowch/components.py
tensorkrowch/embeddings.py
tensorkrowch/initializers.py
tensorkrowch/operations.py
tensorkrowch/utils.py
tensorkrowch/decompositions/__init__.py
tensorkrowch/decompositions/svd_decompositions.py
tensorkrowch/decompositions/tt_decompositions.py
tensorkrowch/models/__init__.py
tensorkrowch/models/mpo.py
tensorkrowch/models/mps.py
tensorkrowch/models/mps_data.py
tensorkrowch/models/peps.py
tensorkrowch/models/tree.py
tensorkrowch-1.1.6.dist-info/LICENSE.txt
tensorkrowch-1.1.6.dist-info/METADATA
tensorkrowch-1.1.6.dist-info/WHEEL
tensorkrowch-1.1.6.dist-info/top_level.txt
tensorkrowch-1.1.6.dist-info/RECORD
