Metadata-Version: 2.2
Name: tensorkrowch
Version: 1.1.6
Summary: Tensor Networks with PyTorch
Author-email: José Ramón Pareja Monturiol <joserapa98@gmail.com>
Maintainer-email: José Ramón Pareja Monturiol <joserapa98@gmail.com>
License: MIT License
Project-URL: GitHub, https://github.com/joserapa98/tensorkrowch
Project-URL: Documentation, https://joserapa98.github.io/tensorkrowch
Keywords: tensor,network,tensor network,tensor networks,mps,mpo,peps,quantum
Requires-Python: >=3.8
License-File: LICENSE.txt
Requires-Dist: torch>=1.9
Requires-Dist: opt_einsum>=3.0
Provides-Extra: tests
Requires-Dist: pytest; extra == "tests"
Requires-Dist: pytest-cov; extra == "tests"
Provides-Extra: docs
Requires-Dist: sphinx==4.5.0; extra == "docs"
Requires-Dist: sphinx-book-theme==0.3.3; extra == "docs"
Requires-Dist: sphinx-copybutton==0.5.2; extra == "docs"
Requires-Dist: sphinxcontrib-applehelp==1.0.4; extra == "docs"
Requires-Dist: sphinxcontrib-devhelp==1.0.2; extra == "docs"
Requires-Dist: sphinxcontrib-htmlhelp==2.0.1; extra == "docs"
Requires-Dist: sphinxcontrib-qthelp==1.0.3; extra == "docs"
Requires-Dist: sphinxcontrib-serializinghtml==1.1.5; extra == "docs"
Requires-Dist: ipykernel; extra == "docs"
Requires-Dist: nbsphinx==0.9.3; extra == "docs"
